{"C4VRrdWCgFrDJrNZl/ESZg==":"ben-bowens-104402-2000x1329.jpg","qRWPuL/IFZQ4oLE2/b5NiA==":"annie-spratt-51436-2000x1056.jpg","U6vKqL8Xavj6trrvS1+JOA==":"mbr-1618x1080.jpg","LxjZr0Hj7+3gX9qjaS7mWg==":"tim-trad-191574-2800x1866.jpg","WuuYi4UNdJQEOzDQ0KWDqQ==":"alexandre-godreau-188906-2800x1866.jpg","WR+SeQS5qgJzG3x0jgnCqg==":"alexandre-godreau-188906.jpg","/H2y26ZQc2JiAQoPSb1hKQ==":"tim-trad-191574.jpg","kRHrrqaTcBEWwR8VZFmbnw==":"isabella-juskova-100382.jpg","CAAP/6lIi3KBaETAUX5m0Q==":"jeremy-bishop-262139.jpg","PWj6o4drz4RcdwAwP/BkBw==":"jeremy-bishop-262140.jpg","botfl0nKqjp3OPOGvdYmKQ==":"isabella-juskova-100383.jpg","FoSy5UoUbHwn2MV4RxvN+g==":"john-salvino-317388.jpg","S6NQDj/mWIm+PLWOuW3rYA==":"forrest-cavale-13484.jpg","xjdIC8t3cgOCeT0rZUeD1A==":"garrett-sears-91351.jpg","+poWKQ9rniNPlNZVVxs5hQ==":"mbr.jpg","mj1Ioe9ZLP5pont/ZaO/5A==":"geoffrey-arduini-176853.jpg","QbzqI2uPScGh7XU/V9U2AA==":"neonbrand-199264.jpg","Nc2MnluNcoH+10zF+Q9ZMw==":"sam-wheeler-2304.jpg","sDmeZ/yaabnEHuJLtzFZQw==":"ishan-seefromthesky-118523.jpg","RAtoVrADBDAchuTWwJ+9Tw==":"mbr-1.jpg","WqtSDfPvwIQWdUme8Xwsew==":"frank-mckenna-222543.jpg","pA3zUve1aSj2b8qbXvcUhw==":"glen-jackson-301620.jpg","SuufhiGBashilNb6lrvNpw==":"guillaume-bolduc-328118.jpg","558T08ajzV2ldZ/0tqQ0pg==":"user-review.jpg","tpIWZNsU9q7OlZ/n23PZ+w==":"elen-laureano-333976-1.jpg","p2Y3OQbnS4SVfJ7kSwYCZg==":"girl.jpg","iRAMe1UTnBHDO3RwSoCG2A==":"nad-hemnani-58324.jpg","6mRm/7YsiZ/1rI5espGUJw==":"purple11-62749.jpg","Z7A0htRC6XXiD9Vx88+cbA==":"mbr-2.jpg","iLOLO8qSfqUhdMtVXRugCA==":"mbr-3.jpg","t94So/PDExnQ9cQSn6tyZA==":"stic%2017197-nr8ll6-01%20%5Brecovered%5D-122x141.png","/mJS2unbyhvbUEA1Fu+TtQ==":"sofitel-hotel-ivoire-abidjan-2-910x606.jpg","mIIbxW0r7dEZSbMPwcoYdg==":"background2.jpg","22ZMedNoL6pre6dhwkTCHw==":"01.jpg","UAc7kepzJPkrSn4uqTRvmw==":"background4.jpg","MDHuCyqtWiLD47dzoLX+8g==":"20020r000000hif084c18_r_600_400_r5_d-600x400.jpg","Q8MW17ps8ZHNXGFHbXqDDA==":"576e769c93509-332x418.jpg","jaNiXSnbD9Vd9Imna5y5eg==":"e8b1408497993c96c78e9ec7b728dbc6-1000x600.jpg","7nPXkYcpmSj7JdUvivTB+w==":"hotel-ivoire-1040x585.jpg","qri289SylhdZY2u3TuZn7g==":"194475232-1010x768.jpg","Clnn921e8KB1etfH7Z9BFw==":"8844_wdfh_00_p_2560x1440-1014x570.jpg","bGsODRYtYPPQGODhWDdWVA==":"2017-07-24-325x433.jpg","xQ93hNyOxm4YyBVrDk5O9A==":"capture%20d%E2%80%99e%CC%81cran%202020-07-14%20a%CC%80%2018.20.44-324x243.jpg","bnQFDPKP8RiLpXuQIApxDg==":"2018-03-6-324x243.jpg","4t7T7rJCCG1EdwRU0Y3wow==":"2017-04-1-325x325.jpg","zj5Q+8k65RgIJ6iLGPXFOw==":"salle%20des%20fetes%20(1)-324x216.jpg","0rQwKtGPi8lcoD3oA7M6Yg==":"unnamed%20(1)-324x243.jpg","dL/MlJOsKFWmzxsuibKsXg==":"img_20151114-122731-325x240.jpg","+BZibn3TlMBq7h5Y8ZeAjg==":"img_1348-01%20-%20copie-324x216.jpg","jJ7wsiTRmhs4JGbxKyc/gg==":"img-9778-324x235.jpg","FqBk3BjFuf5D4vB1CWO4kw==":"230283782-1024x575.jpg","3h9qvV1mTZoU2LiN9MHrHg==":"0e2f30_1b692f642cb14022b98a3732bc63ced3_mv2.webp","wr+Ht1ccgDZS5e4DKaCOyg==":"chez%20arthur%20bassam-676x450.jpg","cf5O+oBcTkAdW6waUzlYrg==":"mvimg_20180802-174548-324x243.jpg","kSRJeaOL6wuOdHtrEzlOng==":"227391707-676x507.jpg","NYKgdtVVv+paRrd9rGUqYw==":"227391707-1024x768.jpg","26098UqjL3kVdSzGnJeCCQ==":"la-baie-des-sirenes-550x413.jpg","Ba3H6j1je2hlfNbKNm4wTQ==":"227391576-676x451.jpg","Wx/dQCMIRiCA+EpTNezVVg==":"230283782-676x380.jpg","adBstG6BmCNs94ONwg7ctg==":"89995441-1024x683.jpg","74fR4m3ZyP3FAzQZBcjRZw==":"230285865-1024x575.jpg","UcLReubD1iuAv2vAUVBcLg==":"ivory_coast-2000x1250.png","KW53QQGBU1IN3rRSudQ0Mg==":"la-baie-des-sirenes%20(1)-1014x761.jpg","OjaQx5UlED012pc0DGRGQg==":"106204497_3015324465189416_1796991689980971261_n-240x236.jpg","W/PXJEbfIw9YMDBrMFWhsg==":"hotel-tiama-1024x768.jpg","LxjXWbe1B8kXTy1peaJbcA==":"104384_v5.webp","dqIrpsdZYD9TeIygtth4MA==":"pix_1551951021e093021-1-1500x780.jpg","5UlezSTXpDkssgep0igS/w==":"hotel-tiama-1-1024x768.jpg","5nw9BoHGDVGQqN3gqcvkWw==":"te%CC%81le%CC%81chargement%20(2)-225x225.jpg","58fx1AM3IncLQYz1qXtafQ==":"_oceanofdmg.com_recoverit_7.2.1.2_tnt-1024x680.jpg","m70YJLckyL5no8oB1RnetA==":"au-bord-de-l-eau-1000x664.jpg","oBgoRPpguiQTcwKQNqzt+w==":"224297025-1200x900.jpg","BY3E5ODY0mblirDg73Pmyw==":"photo0jpg-1024x768.jpg","gw60N8SFwiSjBkJ0rNiIkQ==":"de-la-piscine-on-a-une-960x720.jpg","WDS0Df/OC+nuSZ4SGDizag==":"photo2jpg-1024x768.jpg","7mOVRtGai6kEv1gIWYZFuQ==":"hotel-mon-afrik-1024x768.jpg","ety49eRztXt6gH7hsmbfeQ==":"telechargement-2-225x225-225x225.jpg","pa5Dkwo/T1qgW/t0h+fQvA==":"background5.jpg","LVWNuv0wB5K4udnb3uGJwQ==":"img-20180326-130902-largejpg-1012x759.jpg","+DtcpmVAPXB+xUYCRpKwRA==":"pullman-abidjan-1024x701.jpg","S28SK8uja5xniPVxSRdHMQ==":"enotel-beach-1024x768.jpg","vH4mdBLsi3GNZBkFFO9cAQ==":"hotel-mon-afrik-bouake-1024x768.jpg","zNdupW5zCMtc02EGlW4Klw==":"hotel-sophia-1024x682.jpg","6Js8WTXz0T+ycFyPVybloA==":"residence-hotel-elephant-1024x680.jpg","I+rZV0FjzrX7cOs9bxJoYg==":"hotel-des-parlementaires-1024x682.jpg","iKiw02Uw/BmiZm/M0LwJnQ==":"restaurant-piscine-akwaba%20(1)-1024x784.jpg","C2mMuAK7Df7LSMNuJX+rQw==":"hotel-tiama-1024x683.jpg","LUgxdx8eLH6AC6h8ITa/ew==":"hotel-tiama%20(1)-2000x1333.jpg","UdSvHoD4GglEOTTJa+gWHw==":"chambre-superieure-1024x683.jpg","fWiqrLdaHsd0iPEISOtDQg==":"bar-l-equateur-960x720.jpg","N17ub1kQ2zYChxlmWijwig==":"piscine-akwaba-1024x627.jpg","SPzPtVGw23MJHTcnvYNq5w==":"8844_sl_00_p_1024x768-952x714.jpg","61Z+Q+DoKTF3WolybESk0w==":"8844_sl_00_p_1024x768-952x714.jpeg","Yr/1fP58cXWSrNx4B7KUog==":"8844_sl_00_p_1024x768-1-952x714.jpeg","TYVmckniMsCR9PFe5Z5gnQ==":"hotel-president%20(1)-1024x682.jpg","RX7lClvls4AFEs4TeYKPvg==":"photo0jpg-1-1024x768.jpg","wBzCRiDwfkg1aLaYFzWbtg==":"hotel-president-1024x768.jpg","0t9rWIb4N649fl7in0Cehw==":"hotel-president%20(2)-1024x681.jpg","Qdzn1TMzTfujwaXuudmf8A==":"filename-annex-bedroom-550x412.jpg","uzkApI4abR2riWk4syCtmA==":"130572782-1280x853.jpg","04QzjcFN2QBCcGJTm7XVxg==":"petite-photo-chambre-restauree-hotel-president-yamoussoukro-560x320.jpg","xNBWCjVltzZ9XQ9WByf8+A==":"head_suite_presidentielle_tour4-1280x640.jpg","EH4oh2aR9SDf0bqqyIigng==":"head_suite_presidentielle_tour1-1280x640.jpg","spqLDadAKaeW5dUVsZ5jSw==":"stade-yamoussoukro-1500x630.jpg","KZIJPCfxz2kfvwYL2F/ypw==":"206938656-1000x667.jpg","I0KreYbuwnQbqjfmlldxbA==":"206934384-1024x768.jpg","AuGjesJGxWj/HpNMYY5bzA==":"206935537-1024x768.jpg","X2pT4xONPoYGzU7F868T+A==":"206933538-1024x768.jpg","cVGFRXnQyFDT1CeXHsLV2g==":"206938686-1008x756.jpg","VhhvY0FaYocKeT5hRyiQkw==":"206934343-1024x768.jpg","FinvF/FSditPc3gXa8TUTA==":"206933745-1024x768.jpg","e981zGKZ3tyz5JwHXU3caw==":"206938694-1024x683.jpg","VsLORoYkBJmqldkiTt/Utg==":"la-reception-1024x683.jpg","0H6xLe3tgB0JiCDA5Bn0xw==":"complexe-hotelier-olympe%20(1)-1024x759.jpg","N+zz8FguLyJtKFkO75RbVw==":"complexe-hotelier-olympe-1024x708.jpg","M+BvQpPOwQlYWnN9yC89GQ==":"chambre-classique%20(1)-1024x683.jpg","68SSxOyHzF4nwjrPisLX9w==":"chambre-classique-1024x683.jpg","wethUVqgxmcsDNJWJpK7kA==":"presentation-du-batiment-960x540.jpg","7WCmuMnGKVsECBTEttDBNQ==":"presentation-du-batiment%20(1)-960x635.jpg","kHkt4tB/fe7HmsCy/WoIVw==":"ivory-coast-chicken-dish-982x638.jpg","sT80Y4RCGNBrSInGgrjIuA==":"background3.jpg","OM6hTwqMAQpTVhLcPG86xg==":"background1.jpg","jXjmsH1frDdG2Sv+N1Z7nw==":"chez-ambroise-550x412.jpg","6mL572jozMf7LneYxoNeew==":"chez-ambroise-550x412.jpeg","W481J8YwuPFkVEOT2e0dMQ==":"13641094_1356223067739140_8432621184454940445_o-900x600.jpg","i3AQpPvpqKr7Mf2bBop5Vw==":"13641094_1356223067739140_8432621184454940445_o-900x600.jpeg","VMpEFa67wpdtXZUFxwC0EA==":"13641094_1356223067739140_8432621184454940445_o-1-900x600.jpeg","xOjP4bM5GV0pS7juacrORQ==":"sauce-graine-recette-ivoirienne-placali-pa%CC%82te-manioc-ivorianfood-900x599.jpg","ekBACOVAX0QD7B5C5/BuEA==":"sauce-graine-recette-ivoirienne-placali-pa%CC%82te-manioc-ivorianfood-900x599.jpeg","Wmnd1CUP9Sj41g12fJsLZg==":"33daeebbb014838fdd3c89c4d1bb39ad-900x1350.jpg","au0SXKFfEvOPmWoOjMdO6g==":"poulets-braises-paillote-338x450.jpg","afZXjzXkjfhAvgbCAQshgw==":"garba-cuisine-ivoirienne-ivorianfood-576x576.jpg","PpidT6pIOhgrO2PGKCSZzQ==":"garba-550x416.jpg","1J1FAQKdvwHIm0wMC6Mxmw==":"garba-550x416.jpeg","aRtWl7VkYunjUuH/XIlwrw==":"garba-festival-2000x1334.jpg","GA5AKRWu3BdXDUr1G8bYaw==":"alloko_poisson_au_piment-1024x576.jpg","oOz4GXH86U7GQDn33w+IJQ==":"unnamed2-512x288.jpg","0tYZcBTRF8MJQajRB19e+g==":"formation2-600x211.png","VJrOq/io+BbdpwKxGgnYCg==":"mbr-1920x1033.jpg","z84vfs7FPcFNgr1G+LwpKQ==":"mbr-1920x1080.jpg","/Jr05jhfQ6me9Lk1Z3Veng==":"11333_57d29a2a8f42e-logo-west-africa-security-110x110.jpg","L83sjtas5UOoKz/au6XrBA==":"11334_57d29a6c08e89-picto-plan-west-africa-security-600x725.jpg","HXav1/Onu8EdqBOxfwBaSA==":"11334_57d29a6c08e89-picto-plan-west-africa-security-600x725.jpeg","vSc7BHYYRGa5nAWlfMwSfw==":"5c38b94befaba-equipe-west-africa-cote-ivoire-800x600.png","itWt9HhjPDoRgDObGO7rtA==":"franck-v-04id07izi9m-unsplash-2000x1269.jpg","Z3ie5JsvaoQWZgVzyBtbrQ==":"5c38b94befaba-equipe-west-africa-cote-ivoire-700x525.png","NbuC5EZIYio+s1kmfi6+Hg==":"5c3c9f2538ae3-verrouillage-auto-west-africa-cote-ivoire-700x525.png","ojHBIqHROOjl5jHcoF8jBQ==":"was-sans-fond-273x280.png","7GD432qK8kp9Mqmfg4PnEA==":"facade-west-africa-cote-ivoire-e1566207513658-700x487.png","Rzet/V/exxAdtPPsyGt7cw==":"81900_5dca976d10f30-01visuel-first-securite-cote-ivoire-649x487.jpg","AnPRpcE0jOTvJ2/yaFbY0w==":"81900_5dca976d10f30-01visuel-first-securite-cote-ivoire-649x487.jpeg","RP6Pt0kuENsLtPxKxazOlw==":"81900_5dca976d10f30-01visuel-first-securite-cote-ivoire-1-649x487.jpeg","IawdWsBIB8GGLwve9iCGTg==":"81926_5dca9ce6a86a7-brigade-de-cynophilevisuel-first-securite-cote-ivoire-400x300.jpg","yLmhg9YMukSg1ZpPvcIqVg==":"g2-600x400.jpg","N4uCFlj+Xfk7FJLRYfSMww==":"81926_5dca9ce6a86a7-brigade-de-cynophilevisuel-first-securite-cote-ivoire-400x300.jpeg","UOpoh5F20TOdeyBpccU2xQ==":"g4-600x400.jpg","4/pOLg7m6FU7Q0e7L7MYCQ==":"marisa-teruel-mwwrmrskomu-unsplash-2000x1328.jpg","PV58neAZdoCX03+GayW6SA==":"was-sans-fond-1-273x280.png","YLVAp2Q/3awyhholiALYSw==":"logo_first-250x250.png","rmG/q4oUjW2uRX4b1Bn1jA==":"52470_5c4b3ab416cd9-garde-rapprochee-force-one-securite-cote-ivoire-400x300.png","thGpVrTzWKDepmAttg5DWw==":"6g_0040198e664543ba6598b876cc0e9047-625x258.jpg","BH4am4L39euKj6MOoj4OAw==":"mbr-1920x1271.jpg","NHjsPmMTo/lSNLMVxuwBag==":"mbr-1920x1537.jpg","77gonZm8VqxoA3LXShZtyg==":"mbr-1920x1201.jpg","4TH6RpS8gviE1tFo6262dw==":"0_1_59-200716115042-960x720.jpg","blShC1n78Qm+USWTHpkhGA==":"2_1_59-200716115042-960x720.jpg","Hpd00vvpD3qT5E5TJxNJgg==":"0_40_813-200706035558-1080x720.jpg","pzxxMlTtytVCjTiGG4/lJQ==":"0-40-813-200706035558-800x533.jpeg","WS5QTKhUj0v3rSqQt2kqAg==":"3_40_813-200706035558-556x371.jpg","nmK/vKYlMYSvRAZkLN/H6A==":"1_40_813-200706035558-556x417.jpg","17xTg3zxH8zQx+ai1qpbQg==":"0_40_813-200706035558-556x371.jpg","O76X0syA1hzCN3+ggioUww==":"mane1718-400x400.png","/H4+mxtcXSaHo3baHEEsbg==":"screenshot_20200501-2113012-400x374.png","4IqDAKbqul50g9SKlxnmuA==":"2019_kia_sportage_2_crdi_isg_s-a_1.6_front-2560x1454.jpg","f8wkTf/Xp+MsPgF4Sl4FpQ==":"2019_kia_sportage_2_crdi_isg_s-a_1.6_front-4362x2478.jpg","lfpjZ32es6HAUqoMcvMRRQ==":"2019_kia_sportage_2_crdi_isg_s-a_1.6_front-2000x1136.jpg","wYMiodVi/ehb5Qh0eyuVjg==":"kay-ojvh3njqttq-unsplash-1162x1743.jpg","ZRNTJg3xgkhvN6cExM8Hiw==":"2019_kia_sportage_2_crdi_isg_s-a_1.6_front-243x138.jpeg","BzLyXKsEZYGjoF8lv9AJ7g==":"stic-17197-nr8ll6-01-recovered-1-122x141.png","/cyj+LuC3U1uue6q1s5I8w==":"stic-17197-nr8ll6-01-recovered-2-122x141.png","P6Ct1nJgTEvoi/rVV/uMFw==":"1_40_813-200706035558-556x417.jpeg","u7X/X8l4A2JQZ7jz0Vj+5g==":"0-40-813-200706035558-1080x720-800x533.jpg","iwYpP3QSSnLKgvmGi5GUKw==":"2019-kia-sportage-2-crdi-isg-s-a-1.6-front-2560x1454.jpeg","eDLsNlCWH9cWiTCRdNVPjQ==":"0_40_813-200706035558-556x371.jpeg","0okj3jVxSQHfZNsK1jEIRg==":"1_8_994-200704095931-1040x780.jpg","Ay5IPitk0lFSx01fesEskg==":"0_18_514-200714045938-1000x450.jpg","VKAYtT70M+RcgDF0oz5vOw==":"1_9_285-200704082624-1224x563.jpg","OToPaS6NyBBM+idj95YG7Q==":"vap-5036961208-444x333.jpg","ox7cy89OVTjp2MhiSYZQ5g==":"1_8_155-200516065034-1024x768.jpg","E0B1fJuVeTzVVFzFGYVAkg==":"1_39_792-200406013149-1008x756.jpg","87xgJ5nZOA5KeqCyt3LRjQ==":"0_9_290-200302025926-576x768.jpg","dW15g+dfsJ0kk1jp94n4gQ==":"5c3c9f2538ae3-verrouillage-auto-west-africa-cote-ivoire-696x522.png","SUwk46trRXB8/p/EOXpnBQ==":"franck-v-04id07izi9m-unsplash-696x442.jpg","AMZQthe6mLgApPgjDqm5RQ==":"sebastian-scholz-nuki-ijksskfeqrm-unsplash-696x464.jpg","GoQpFf4W360L6BFYBAoAYw==":"capture%20d%E2%80%99e%CC%81cran%202020-07-20%20a%CC%80%2021.18.59-696x435.png","iVYJCtVziuvLGUIRao4u4w==":"capture%20d%E2%80%99e%CC%81cran%202020-07-20%20a%CC%80%2021.18.59-696x435.png","00zZUyXhpQoaC0uKo25qvA==":"product1.jpg","ynKQ4dGweSAjbDlaQKGdhw==":"mvyv95hnopy08bbxepb2-935x527.jpg","CsFqd1d5MCg8ecPQPepkEQ==":"zoo-abidjan-1200x800.jpg","mcOWtZX0kW1eQ6qQym5SzA==":"zoo-dabidjan-853x480.jpg","qAMT5ZgZZCEyt5prCDNE3w==":"zoo-abidjan-774x516.jpg","/CNRrX1p/q6dtDQOd8mmRA==":"cathe%CC%81drale_saint-paul_d%E2%80%99abidjan-1280x780.jpg","oVxB5dbXIBiUXq1bqhowHw==":"zoo-dabidjan-774x436.jpg","vtKnuCzKHrjW9BbyTa38XA==":"unnamed%20(1)-512x464.jpg","q+l1xw/h+YA0nY5QLc6Z3g==":"satde_yamoussoukro_scau-780x600.jpg","eZL28i2qs9UxVf+YQiUPzA==":"grande_mosquee-asoal-665x365.jpg","uA5pc+dLGAOwiVxbleltmQ==":"basilique-notre-dame-de-la-paix-de-yamoussoukro-2-818x498.jpg","L1z0zz6Sr0wMDNPvTY5o0A==":"cathe%CC%81drale_saint-paul_d%E2%80%99abidjan-1094x667.jpg","l8AXoPe4THiIdb6l1nV2Qg==":"stade-fe%CC%81lix-houphoue%CC%88t-boigny-960x720.jpg","flbAYDZM+WvUri0tpE7J2g==":"6553bd8eae983654c05178ceaddb8fc7-735x400.jpg","ZNZ1HlH3qy/TzqnKldgNlg==":"poro_korhogo-800x529.jpg","3dqJq+f25fwucT8JF2ywmw==":"dscn0361-1094x821.jpg","pZHpfffkmV4Y17Y+nktrxg==":"whatsapp%20image%202020-01-11%20at%202.10.50%20am-510x510.jpg","PS1o940UuwpWEIfWRwflbQ==":"20200721-23005-510x621.jpg","U4JrKGQBr+ZUK8CEvd9Q9A==":"photo%20marc%20adoni-510x383.jpeg","m3ioqgwmIwrmQ417ycWkKg==":"20200721-24901-510x680.jpg","B6meX7laG76J+HGB2OtWeg==":"photo%20marc%20adoni-510x680.jpg","SrkmvwLr4o1nxC/Kdkzr+A==":"20200721-141851-510x680.jpg","kGpumqJwtXs9tjEaQFnm3A==":"35e369ec6820a693b50fe0eda7a9e4d3-537x800.jpg","7W6yp3shsUoMy+wUAWfifg==":"35e369ec6820a693b50fe0eda7a9e4d3-537x800.jpeg","2iGVQHhg/1+lG2+b8POZlw==":"e345bcf6cc9442c31127cdd1ef493632-479x719.jpg","DfdRDwVV+Aos0OmwgjG/Qw==":"e345bcf6cc9442c31127cdd1ef493632-479x719.jpeg","mxevz6YZXateolJ0J8Wm8Q==":"e345bcf6cc9442c31127cdd1ef493632-1-479x719.jpeg"}